[{"tempoMapLock": false, "bonusAvailable": 0, "videoRequest": 0, "albumImages": [{"albumImageId": "5cf6dcc8-95af-4f10-ba2e-3a520d9c50ab", "height": 1425, "width": 1425, "territoryCode": "worldwide"}], "totalArrangements": 6, "hasUGCGuitarArrangement": false, "hasUGCBassArrangement": false, "hasUGCPianoArrangement": false, "hasOfficialGuitarArrangement": true, "hasOfficialBassArrangement": true, "hasOfficialPianoArrangement": true, "hasArrangementTypes": [11, 15, 10, 8, 4, 14], "lyrics": true, "lenghtFormatted": null, "verifiedTempo": true, "songId": "28065c8f-a636-14a8-107d-9422b87b08e6", "songName": "F.O.D.", "songYear": 1994, "songLength": 170.76, "artistName": "Green Day", "albumName": "Dookie", "albumId": "1b5e96f7-2c64-4974-89cb-6ab70a9990db", "genre": "Rock,Punk Rock,Punk", "explicit": true, "isRegionallyRestricted": false, "isCover": false, "publishedwithin30days": false}, {"tempoMapLock": false, "bonusAvailable": 0, "videoRequest": 0, "albumImages": [{"albumImageId": "0bb128dc-0a86-4772-b935-16109c67aee6", "height": 1400, "width": 1400, "territoryCode": "worldwide"}], "totalArrangements": 3, "hasUGCGuitarArrangement": false, "hasUGCBassArrangement": true, "hasUGCPianoArrangement": false, "hasOfficialGuitarArrangement": false, "hasOfficialBassArrangement": false, "hasOfficialPianoArrangement": false, "hasArrangementTypes": [11, 10, 8], "lyrics": false, "lenghtFormatted": null, "verifiedTempo": true, "songId": "0cf82a49-f710-b149-c160-dc46cb343c8c", "songName": "Four Horsemen Remastered", "songYear": 2013, "songLength": 175.0, "artistName": "The Clash", "albumName": "London Calling (Remastered)", "albumId": "c49b121d-0f26-fa1c-7a85-d5dfb86b0a95", "genre": "Rock,Punk Rock,Punk", "explicit": false, "isRegionallyRestricted": false, "isCover": false, "publishedwithin30days": false}, {"tempoMapLock": false, "bonusAvailable": 0, "videoRequest": 0, "albumImages": [{"albumImageId": "e8c84bce-07f7-41ac-b78f-1c9ebb097f6a", "height": 1400, "width": 1400, "territoryCode": "worldwide"}], "totalArrangements": 2, "hasUGCGuitarArrangement": false, "hasUGCBassArrangement": false, "hasUGCPianoArrangement": false, "hasOfficialGuitarArrangement": false, "hasOfficialBassArrangement": false, "hasOfficialPianoArrangement": false, "hasArrangementTypes": [11, 10], "lyrics": true, "lenghtFormatted": null, "verifiedTempo": true, "songId": "d92efc58-fedf-be4b-4d34-72e06cc546ad", "songName": "Friends Like You Main Version - Explicit", "songYear": 2006, "songLength": 147.0, "artistName": "Bowling For Soup", "albumName": "The Great Burrito Extortion Case", "albumId": "da065115-071a-bcc5-ed73-26d4a1e9dc91", "genre": "Rock,Pop,Punk Rock,Punk", "explicit": true, "isRegionallyRestricted": false, "isCover": false, "publishedwithin30days": false}, {"tempoMapLock": false, "bonusAvailable": 0, "videoRequest": 0, "albumImages": [{"albumImageId": "ea89dc87-9a58-4027-9189-10bbecce6e41", "height": 3000, "width": 3000, "territoryCode": "worldwide"}], "totalArrangements": 3, "hasUGCGuitarArrangement": false, "hasUGCBassArrangement": true, "hasUGCPianoArrangement": false, "hasOfficialGuitarArrangement": false, "hasOfficialBassArrangement": false, "hasOfficialPianoArrangement": false, "hasArrangementTypes": [11, 10, 8], "lyrics": false, "lenghtFormatted": null, "verifiedTempo": true, "songId": "989324c8-3fd8-abe4-74d3-d6ed041d127d", "songName": "Fun", "songYear": 2014, "songLength": 127.0, "artistName": "Murphy's Law", "albumName": "Murphy's Law", "albumId": "b5394444-88f6-5eb0-9af2-961acc9f3af4", "genre": "Rock,Punk Rock,Punk", "explicit": false, "isRegionallyRestricted": false, "isCover": false, "publishedwithin30days": false}, {"tempoMapLock": false, "bonusAvailable": 0, "videoRequest": 0, "albumImages": [{"albumImageId": "c9e534e5-2856-411a-938b-fb2b7bf899aa", "height": 1400, "width": 1400, "territoryCode": "worldwide"}], "totalArrangements": 4, "hasUGCGuitarArrangement": false, "hasUGCBassArrangement": false, "hasUGCPianoArrangement": false, "hasOfficialGuitarArrangement": true, "hasOfficialBassArrangement": true, "hasOfficialPianoArrangement": false, "hasArrangementTypes": [11, 10, 8, 4], "lyrics": false, "lenghtFormatted": null, "verifiedTempo": true, "songId": "8cc9c505-bff0-d591-39da-7a43dcd8caab", "songName": "Garageland Remastered", "songYear": 2013, "songLength": 191.0, "artistName": "The Clash", "albumName": "The Clash (Remastered)", "albumId": "38d814f1-bfae-37d1-6d47-46ca610967e4", "genre": "Rock,Punk Rock,Punk", "explicit": false, "isRegionallyRestricted": false, "isCover": false, "publishedwithin30days": false}, {"tempoMapLock": false, "bonusAvailable": 0, "videoRequest": 0, "albumImages": [{"albumImageId": "9c3cb2f0-5b77-48bc-ae29-ebf6e74f3a66", "height": 1400, "width": 1400, "territoryCode": "worldwide"}], "totalArrangements": 3, "hasUGCGuitarArrangement": false, "hasUGCBassArrangement": true, "hasUGCPianoArrangement": false, "hasOfficialGuitarArrangement": false, "hasOfficialBassArrangement": false, "hasOfficialPianoArrangement": false, "hasArrangementTypes": [11, 8, 10], "lyrics": true, "lenghtFormatted": null, "verifiedTempo": true, "songId": "743c8abd-8e25-347d-9ceb-68a8d843ccf6", "songName": "Gates of the West", "songYear": 2013, "songLength": 205.0, "artistName": "The Clash", "albumName": "The Cost of Living - EP", "albumId": "30c10db5-4931-98e1-8249-916003598151", "genre": "Rock,Punk Rock,Punk", "explicit": false, "isRegionallyRestricted": false, "isCover": false, "publishedwithin30days": false}, {"tempoMapLock": false, "bonusAvailable": 0, "videoRequest": 0, "albumImages": [{"albumImageId": "d142dbec-6aab-4b23-bf1b-931a40c63fc5", "height": 1400, "width": 1400, "territoryCode": "worldwide"}], "totalArrangements": 3, "hasUGCGuitarArrangement": false, "hasUGCBassArrangement": true, "hasUGCPianoArrangement": false, "hasOfficialGuitarArrangement": false, "hasOfficialBassArrangement": false, "hasOfficialPianoArrangement": false, "hasArrangementTypes": [11, 10, 8], "lyrics": true, "lenghtFormatted": null, "verifiedTempo": true, "songId": "088c6bcc-c15f-1195-c39d-0f0960dcf7c0", "songName": "Girl", "songYear": 1996, "songLength": 244.0, "artistName": "FAR", "albumName": "Tin Cans With Strings To You", "albumId": "60184a4e-8655-4162-9f45-e0592f5a04c6", "genre": "Rock,Punk Rock,Punk", "explicit": false, "isRegionallyRestricted": false, "isCover": false, "publishedwithin30days": false}, {"tempoMapLock": false, "bonusAvailable": 0, "videoRequest": 0, "albumImages": [{"albumImageId": "34cb3584-47cb-4cc8-b09a-92e7ef14a516", "height": 1400, "width": 1400, "territoryCode": "Worldwide"}], "totalArrangements": 2, "hasUGCGuitarArrangement": false, "hasUGCBassArrangement": false, "hasUGCPianoArrangement": false, "hasOfficialGuitarArrangement": false, "hasOfficialBassArrangement": false, "hasOfficialPianoArrangement": false, "hasArrangementTypes": [11, 10], "lyrics": true, "lenghtFormatted": null, "verifiedTempo": true, "songId": "2b31977f-0a0b-8578-4d1c-cf5d9553fdbf", "songName": "Greatest Day", "songYear": 2002, "songLength": 199.0, "artistName": "Bowling For Soup", "albumName": "Drunk Enough To Dance", "albumId": "69d31738-47aa-484b-a3dc-18a5a8bc58f0", "genre": "Rock,Pop,Punk Rock,Punk", "explicit": false, "isRegionallyRestricted": false, "isCover": false, "publishedwithin30days": false}, {"tempoMapLock": false, "bonusAvailable": 0, "videoRequest": 0, "albumImages": [{"albumImageId": "9c3cb2f0-5b77-48bc-ae29-ebf6e74f3a66", "height": 1400, "width": 1400, "territoryCode": "worldwide"}], "totalArrangements": 3, "hasUGCGuitarArrangement": false, "hasUGCBassArrangement": true, "hasUGCPianoArrangement": false, "hasOfficialGuitarArrangement": false, "hasOfficialBassArrangement": false, "hasOfficialPianoArrangement": false, "hasArrangementTypes": [11, 10, 8], "lyrics": false, "lenghtFormatted": null, "verifiedTempo": true, "songId": "74fa3579-e8f6-5042-66fe-505f433fc852", "songName": "Groovy Times", "songYear": 2013, "songLength": 210.0, "artistName": "The Clash", "albumName": "The Cost of Living - EP", "albumId": "30c10db5-4931-98e1-8249-916003598151", "genre": "Rock,Punk Rock,Punk", "explicit": false, "isRegionallyRestricted": false, "isCover": false, "publishedwithin30days": false}, {"tempoMapLock": false, "bonusAvailable": 0, "videoRequest": 0, "albumImages": [{"albumImageId": "ff4fc3ed-6660-4910-810c-5406241f4c35", "height": 1400, "width": 1400, "territoryCode": "worldwide"}], "totalArrangements": 3, "hasUGCGuitarArrangement": false, "hasUGCBassArrangement": true, "hasUGCPianoArrangement": false, "hasOfficialGuitarArrangement": false, "hasOfficialBassArrangement": false, "hasOfficialPianoArrangement": false, "hasArrangementTypes": [11, 10, 8], "lyrics": false, "lenghtFormatted": null, "verifiedTempo": true, "songId": "87a9d3a3-44ff-3764-3d55-832f64c5a830", "songName": "Guns on the Roof Remastered", "songYear": 2013, "songLength": 195.0, "artistName": "The Clash", "albumName": "Give 'Em Enough Rope (Remastered)", "albumId": "a7bd41de-9380-5569-1362-de0ad401c0b4", "genre": "Rock,Punk Rock,Punk", "explicit": false, "isRegionallyRestricted": false, "isCover": false, "publishedwithin30days": false}, {"tempoMapLock": false, "bonusAvailable": 0, "videoRequest": 0, "albumImages": [{"albumImageId": "0bb128dc-0a86-4772-b935-16109c67aee6", "height": 1400, "width": 1400, "territoryCode": "worldwide"}], "totalArrangements": 3, "hasUGCGuitarArrangement": false, "hasUGCBassArrangement": true, "hasUGCPianoArrangement": false, "hasOfficialGuitarArrangement": false, "hasOfficialBassArrangement": false, "hasOfficialPianoArrangement": false, "hasArrangementTypes": [11, 10, 8], "lyrics": false, "lenghtFormatted": null, "verifiedTempo": true, "songId": "ad891f84-a405-45c9-e5f9-58e658bf17f0", "songName": "Hateful Remastered", "songYear": 2013, "songLength": 163.0, "artistName": "The Clash", "albumName": "London Calling (Remastered)", "albumId": "c49b121d-0f26-fa1c-7a85-d5dfb86b0a95", "genre": "Rock,Punk Rock,Punk", "explicit": false, "isRegionallyRestricted": false, "isCover": false, "publishedwithin30days": false}, {"tempoMapLock": false, "bonusAvailable": 0, "videoRequest": 0, "albumImages": [{"albumImageId": "c9e534e5-2856-411a-938b-fb2b7bf899aa", "height": 1400, "width": 1400, "territoryCode": "worldwide"}], "totalArrangements": 5, "hasUGCGuitarArrangement": false, "hasUGCBassArrangement": true, "hasUGCPianoArrangement": false, "hasOfficialGuitarArrangement": true, "hasOfficialBassArrangement": true, "hasOfficialPianoArrangement": false, "hasArrangementTypes": [11, 10, 8, 8, 4], "lyrics": true, "lenghtFormatted": null, "verifiedTempo": true, "songId": "403e36a1-3898-1a53-d63c-151e33fb333f", "songName": "Hate & War Remastered", "songYear": 2013, "songLength": 126.0, "artistName": "The Clash", "albumName": "The Clash (Remastered)", "albumId": "38d814f1-bfae-37d1-6d47-46ca610967e4", "genre": "Rock,Punk Rock,Punk", "explicit": false, "isRegionallyRestricted": false, "isCover": false, "publishedwithin30days": false}, {"tempoMapLock": false, "bonusAvailable": 0, "videoRequest": 0, "albumImages": [{"albumImageId": "a0707b73-bb89-4e5d-8a3c-515540abcf94", "height": 1440, "width": 1440, "territoryCode": "worldwide"}], "totalArrangements": 4, "hasUGCGuitarArrangement": false, "hasUGCBassArrangement": false, "hasUGCPianoArrangement": false, "hasOfficialGuitarArrangement": true, "hasOfficialBassArrangement": true, "hasOfficialPianoArrangement": false, "hasArrangementTypes": [11, 10, 8, 4], "lyrics": true, "lenghtFormatted": null, "verifiedTempo": true, "songId": "a63ef026-3e20-c647-92cc-012c23ff27f3", "songName": "Haushinka", "songYear": 2009, "songLength": 205.44, "artistName": "Green Day", "albumName": "Nimrod", "albumId": "e1686beb-d712-8f8a-2b5d-143ed3538e55", "genre": "Rock,Punk Rock,Punk", "explicit": false, "isRegionallyRestricted": false, "isCover": false, "publishedwithin30days": false}, {"tempoMapLock": false, "bonusAvailable": 0, "videoRequest": 0, "albumImages": [{"albumImageId": "5cf6dcc8-95af-4f10-ba2e-3a520d9c50ab", "height": 1425, "width": 1425, "territoryCode": "worldwide"}], "totalArrangements": 4, "hasUGCGuitarArrangement": true, "hasUGCBassArrangement": true, "hasUGCPianoArrangement": false, "hasOfficialGuitarArrangement": false, "hasOfficialBassArrangement": false, "hasOfficialPianoArrangement": false, "hasArrangementTypes": [11, 8, 10, 4], "lyrics": true, "lenghtFormatted": null, "verifiedTempo": true, "songId": "98bd065c-19bf-d75d-2abe-aa5ca2bc0327", "songName": "Having a Blast", "songYear": 1994, "songLength": 164.667, "artistName": "Green Day", "albumName": "Dookie", "albumId": "1b5e96f7-2c64-4974-89cb-6ab70a9990db", "genre": "Rock,Punk Rock,Punk", "explicit": false, "isRegionallyRestricted": false, "isCover": false, "publishedwithin30days": false}, {"tempoMapLock": false, "bonusAvailable": 0, "videoRequest": 0, "albumImages": [{"albumImageId": "d8c8155b-3e69-483f-9e41-fcf1cdf3d8b2", "height": 1251, "width": 1400, "territoryCode": "worldwide"}], "totalArrangements": 2, "hasUGCGuitarArrangement": false, "hasUGCBassArrangement": false, "hasUGCPianoArrangement": false, "hasOfficialGuitarArrangement": false, "hasOfficialBassArrangement": false, "hasOfficialPianoArrangement": false, "hasArrangementTypes": [10, 11], "lyrics": false, "lenghtFormatted": null, "verifiedTempo": true, "songId": "d9df07af-6304-5a76-d1aa-e7ad97ccc75c", "songName": "Heart and Mind", "songYear": 2004, "songLength": 267.0, "artistName": "The Clash", "albumName": "London Calling", "albumId": "d6aa919f-b01a-cdc0-ae50-d9bd291e0780", "genre": "Rock,Punk Rock,Punk", "explicit": false, "isRegionallyRestricted": false, "isCover": false, "publishedwithin30days": false}, {"tempoMapLock": false, "bonusAvailable": 0, "videoRequest": 0, "albumImages": [{"albumImageId": "600c4685-c9d3-4095-9a58-45efa20ca707", "height": 3000, "width": 3000, "territoryCode": "worldwide"}], "totalArrangements": 3, "hasUGCGuitarArrangement": false, "hasUGCBassArrangement": true, "hasUGCPianoArrangement": false, "hasOfficialGuitarArrangement": false, "hasOfficialBassArrangement": false, "hasOfficialPianoArrangement": false, "hasArrangementTypes": [11, 10, 8], "lyrics": false, "lenghtFormatted": null, "verifiedTempo": true, "songId": "d02869c7-eac9-82fa-848b-f38c22b7d641", "songName": "Heatstroke", "songYear": 2020, "songLength": 140.0, "artistName": "The Chats", "albumName": "High Risk Behaviour", "albumId": "4749b0e5-2f36-0207-a442-91b9e561befe", "genre": "Rock,Punk Rock,Punk", "explicit": true, "isRegionallyRestricted": false, "isCover": false, "publishedwithin30days": false}, {"tempoMapLock": false, "bonusAvailable": 0, "videoRequest": 0, "albumImages": [{"albumImageId": "9a8d77c6-bf72-43f5-bb57-3da6b48b98af", "height": 1400, "width": 1400, "territoryCode": "worldwide"}], "totalArrangements": 2, "hasUGCGuitarArrangement": false, "hasUGCBassArrangement": false, "hasUGCPianoArrangement": false, "hasOfficialGuitarArrangement": false, "hasOfficialBassArrangement": false, "hasOfficialPianoArrangement": false, "hasArrangementTypes": [10, 11], "lyrics": false, "lenghtFormatted": null, "verifiedTempo": true, "songId": "60d358df-efe3-ec04-d04e-9ffedb845798", "songName": "Hell's Eight Acres", "songYear": 2005, "songLength": 232.0, "artistName": "Adam Ant", "albumName": "Vive Le Rock", "albumId": "0d33d10a-afb7-963f-ac57-fab4925e2987", "genre": "Rock,Punk Rock,Punk", "explicit": false, "isRegionallyRestricted": false, "isCover": false, "publishedwithin30days": false}, {"tempoMapLock": false, "bonusAvailable": 0, "videoRequest": 0, "albumImages": [{"albumImageId": "bceeacce-fcc7-406c-9adb-954ea0389b29", "height": 1440, "width": 1440, "territoryCode": "worldwide"}], "totalArrangements": 5, "hasUGCGuitarArrangement": true, "hasUGCBassArrangement": false, "hasUGCPianoArrangement": false, "hasOfficialGuitarArrangement": true, "hasOfficialBassArrangement": true, "hasOfficialPianoArrangement": false, "hasArrangementTypes": [5, 10, 11, 4, 8], "lyrics": true, "lenghtFormatted": null, "verifiedTempo": true, "songId": "c1cf9761-65c0-51eb-4a3a-74b656a15c7b", "songName": "Hitchin' a Ride", "songYear": 1997, "songLength": 171.467, "artistName": "Green Day", "albumName": "Nimrod", "albumId": "1c9ddf48-efa9-4a99-a9c1-33cf5ada430b", "genre": "Rock,Punk Rock,Punk", "explicit": false, "isRegionallyRestricted": false, "isCover": false, "publishedwithin30days": false}, {"tempoMapLock": false, "bonusAvailable": 0, "videoRequest": 0, "albumImages": [{"albumImageId": "1bae015f-9d3d-4983-a24e-24a14baebe16", "height": 1400, "width": 1400, "territoryCode": "worldwide"}], "totalArrangements": 3, "hasUGCGuitarArrangement": false, "hasUGCBassArrangement": true, "hasUGCPianoArrangement": false, "hasOfficialGuitarArrangement": false, "hasOfficialBassArrangement": false, "hasOfficialPianoArrangement": false, "hasArrangementTypes": [11, 10, 8], "lyrics": true, "lenghtFormatted": null, "verifiedTempo": true, "songId": "2b90e799-0568-d47c-bb1f-e1370062ce74", "songName": "Hitsville U.K. Remastered", "songYear": 2013, "songLength": 262.0, "artistName": "The Clash", "albumName": "Sandinista! (Remastered)", "albumId": "789044b3-c4f0-e1c7-9fdf-fd7e5a503fde", "genre": "Rock,Pop,Punk Rock,Punk", "explicit": false, "isRegionallyRestricted": false, "isCover": false, "publishedwithin30days": false}, {"tempoMapLock": false, "bonusAvailable": 0, "videoRequest": 0, "albumImages": [{"albumImageId": "4336ce68-9bf7-42e3-9cf9-8a55b16a5669", "height": 1425, "width": 1425, "territoryCode": "worldwide"}], "totalArrangements": 5, "hasUGCGuitarArrangement": false, "hasUGCBassArrangement": false, "hasUGCPianoArrangement": false, "hasOfficialGuitarArrangement": true, "hasOfficialBassArrangement": true, "hasOfficialPianoArrangement": false, "hasArrangementTypes": [11, 4, 8, 6, 10], "lyrics": true, "lenghtFormatted": null, "verifiedTempo": true, "songId": "674257b0-b0f0-5b95-1814-131171307d64", "songName": "Holiday", "songYear": 2004, "songLength": 232.68, "artistName": "Green Day", "albumName": "Greatest Hits: God's Favorite Band", "albumId": "8596485b-6323-be01-9e77-3f9b316fcd2e", "genre": "Rock,Punk Rock,Punk", "explicit": true, "isRegionallyRestricted": false, "isCover": false, "publishedwithin30days": false}, {"tempoMapLock": false, "bonusAvailable": 0, "videoRequest": 0, "albumImages": [{"albumImageId": "e14e4ef9-eeeb-41dd-b0c4-fece5dc25174", "height": 3000, "width": 3000, "territoryCode": "worldwide"}], "totalArrangements": 2, "hasUGCGuitarArrangement": false, "hasUGCBassArrangement": false, "hasUGCPianoArrangement": false, "hasOfficialGuitarArrangement": false, "hasOfficialBassArrangement": false, "hasOfficialPianoArrangement": false, "hasArrangementTypes": [10, 11], "lyrics": false, "lenghtFormatted": null, "verifiedTempo": true, "songId": "eb1aee99-a6e1-bb48-d754-255cfbd446ed", "songName": "Hopeless Romantic", "songYear": 2011, "songLength": 103.0, "artistName": "Bouncing Souls", "albumName": "Live", "albumId": "2ff65eaa-9252-85d2-5d0a-acf09ef247e9", "genre": "Rock,Punk Rock,Punk", "explicit": false, "isRegionallyRestricted": false, "isCover": false, "publishedwithin30days": false}, {"tempoMapLock": false, "bonusAvailable": 0, "videoRequest": 0, "albumImages": [{"albumImageId": "f4430e95-b407-43c0-806d-38d4e325e4ef", "height": 3000, "width": 3000, "territoryCode": "worldwide"}], "totalArrangements": 3, "hasUGCGuitarArrangement": false, "hasUGCBassArrangement": true, "hasUGCPianoArrangement": false, "hasOfficialGuitarArrangement": false, "hasOfficialBassArrangement": false, "hasOfficialPianoArrangement": false, "hasArrangementTypes": [10, 11, 8], "lyrics": false, "lenghtFormatted": null, "verifiedTempo": true, "songId": "1f8a6706-2bfb-35d7-6259-c2b08766b056", "songName": "How Sad", "songYear": 1990, "songLength": 120.0, "artistName": "The Adicts", "albumName": "Rockers Into Orbit", "albumId": "58858f78-4c63-31f0-b57c-f383b9cd0155", "genre": "Rock,Punk Rock,Punk", "explicit": false, "isRegionallyRestricted": false, "isCover": false, "publishedwithin30days": false}, {"tempoMapLock": false, "bonusAvailable": 0, "videoRequest": 0, "albumImages": [{"albumImageId": "f4430e95-b407-43c0-806d-38d4e325e4ef", "height": 3000, "width": 3000, "territoryCode": "worldwide"}], "totalArrangements": 2, "hasUGCGuitarArrangement": false, "hasUGCBassArrangement": false, "hasUGCPianoArrangement": false, "hasOfficialGuitarArrangement": false, "hasOfficialBassArrangement": false, "hasOfficialPianoArrangement": false, "hasArrangementTypes": [10, 11], "lyrics": true, "lenghtFormatted": null, "verifiedTempo": true, "songId": "cee7c81f-9484-0eca-d97a-df31b076fb56", "songName": "Hurt", "songYear": 1990, "songLength": 198.0, "artistName": "The Adicts", "albumName": "Rockers Into Orbit", "albumId": "58858f78-4c63-31f0-b57c-f383b9cd0155", "genre": "Rock,Punk Rock,Punk", "explicit": false, "isRegionallyRestricted": false, "isCover": false, "publishedwithin30days": false}, {"tempoMapLock": false, "bonusAvailable": 0, "videoRequest": 0, "albumImages": [{"albumImageId": "600c4685-c9d3-4095-9a58-45efa20ca707", "height": 3000, "width": 3000, "territoryCode": "worldwide"}], "totalArrangements": 5, "hasUGCGuitarArrangement": true, "hasUGCBassArrangement": true, "hasUGCPianoArrangement": false, "hasOfficialGuitarArrangement": false, "hasOfficialBassArrangement": false, "hasOfficialPianoArrangement": false, "hasArrangementTypes": [11, 6, 10, 8, 4], "lyrics": false, "lenghtFormatted": null, "verifiedTempo": true, "songId": "376c1954-7da8-883d-96a2-487b2e8e6d2f", "songName": "Identity Theft", "songYear": 2020, "songLength": 162.0, "artistName": "The Chats", "albumName": "High Risk Behaviour", "albumId": "4749b0e5-2f36-0207-a442-91b9e561befe", "genre": "Rock,Punk Rock,Punk", "explicit": true, "isRegionallyRestricted": false, "isCover": false, "publishedwithin30days": false}, {"tempoMapLock": false, "bonusAvailable": 0, "videoRequest": 0, "albumImages": [{"albumImageId": "34cb3584-47cb-4cc8-b09a-92e7ef14a516", "height": 1400, "width": 1400, "territoryCode": "Worldwide"}], "totalArrangements": 2, "hasUGCGuitarArrangement": false, "hasUGCBassArrangement": false, "hasUGCPianoArrangement": false, "hasOfficialGuitarArrangement": false, "hasOfficialBassArrangement": false, "hasOfficialPianoArrangement": false, "hasArrangementTypes": [10, 11], "lyrics": false, "lenghtFormatted": null, "verifiedTempo": true, "songId": "f79abfbc-8cdb-dedc-c795-cf40c859f369", "songName": "I Don't Wanna Rock", "songYear": 2002, "songLength": 183.0, "artistName": "Bowling For Soup", "albumName": "Drunk Enough To Dance", "albumId": "69d31738-47aa-484b-a3dc-18a5a8bc58f0", "genre": "Rock,Pop,Punk Rock,Punk", "explicit": false, "isRegionallyRestricted": false, "isCover": false, "publishedwithin30days": false}]